datascrub/__init__.py
datascrub/cleaner.py
datascrub/datascrub.py
datascrub-1.1.5.dist-info/LICENSE.txt
datascrub-1.1.5.dist-info/METADATA
datascrub-1.1.5.dist-info/WHEEL
datascrub-1.1.5.dist-info/top_level.txt
datascrub-1.1.5.dist-info/RECORD
