Metadata-Version: 2.1
Name: datascrub
Version: 1.1.5
Summary: A Python package for cleaning and preprocessing data in pandas DataFrames
Home-page: https://github.com/samuelshine/cleanmydata
Author: Samuel Shine
Author-email: samuelshine112003@gmail.com
Classifier: Development Status :: 5 - Production/Stable
Classifier: License :: OSI Approved :: MIT License
Classifier: Programming Language :: Python :: 3
Classifier: Programming Language :: Python :: 3.6
Classifier: Programming Language :: Python :: 3.7
Classifier: Programming Language :: Python :: 3.8
Classifier: Programming Language :: Python :: 3.9
License-File: LICENSE.txt
Requires-Dist: pandas
Requires-Dist: numpy
Requires-Dist: charset-normalizer
Requires-Dist: fuzzywuzzy
Requires-Dist: scipy
Requires-Dist: emoji
Requires-Dist: googletrans
